unquietcode/tools/markt/__init__.py
unquietcode/tools/markt/helpers.py
unquietcode/tools/markt/terminal_renderer.py
markt-0.0.dist-info/METADATA
markt-0.0.dist-info/WHEEL
markt-0.0.dist-info/top_level.txt
markt-0.0.dist-info/RECORD
